code_rag/__init__.py
code_rag/__main__.py
code_rag/api.py
code_rag/embedding_server.py
code_rag/logger.py
code_rag/main.py
code_rag/mcp_server.py
code_rag/setup_wizard.py
code_rag/config/__init__.py
code_rag/config/config.py
code_rag/database/__init__.py
code_rag/database/chroma_database.py
code_rag/database/database_interface.py
code_rag/database/qdrant_database.py
code_rag/embeddings/__init__.py
code_rag/embeddings/embedding_interface.py
code_rag/embeddings/http_embedding.py
code_rag/embeddings/litellm_embedding.py
code_rag/embeddings/openai_embedding.py
code_rag/embeddings/sentence_transformer_embedding.py
code_rag/index/__init__.py
code_rag/index/metadata_index.py
code_rag/processor/__init__.py
code_rag/processor/file_processor.py
code_rag/processor/syntax_chunker.py
code_rag/reranker/__init__.py
code_rag/reranker/cross_encoder_reranker.py
code_rag/reranker/http_reranker.py
code_rag/reranker/reranker_interface.py
code_rag/search/__init__.py
code_rag/search/query_analyzer.py
code_rag_mcp-0.3.4.dist-info/licenses/LICENSE
code_rag_mcp-0.3.4.dist-info/METADATA
code_rag_mcp-0.3.4.dist-info/WHEEL
code_rag_mcp-0.3.4.dist-info/entry_points.txt
code_rag_mcp-0.3.4.dist-info/top_level.txt
code_rag_mcp-0.3.4.dist-info/RECORD
