Metadata-Version: 2.4
Name: code-rag-mcp
Version: 0.3.4
Summary: MCP server for efficient code search
Author-email: Duc Nguyen <duc@qduc.me>
License: MIT License
Project-URL: Homepage, https://github.com/qduc/code-rag
Project-URL: Issues, https://github.com/qduc/code-rag/issues
Keywords: rag,code-search,embeddings,semantic-search,mcp
Classifier: Development Status :: 3 - Alpha
Classifier: Intended Audience :: Developers
Classifier: License :: OSI Approved :: MIT License
Classifier: Programming Language :: Python :: 3
Classifier: Programming Language :: Python :: 3.8
Classifier: Programming Language :: Python :: 3.9
Classifier: Programming Language :: Python :: 3.10
Classifier: Programming Language :: Python :: 3.11
Classifier: Topic :: Scientific/Engineering :: Artificial Intelligence
Classifier: Topic :: Software Development :: Libraries :: Python Modules
Requires-Python: <3.14,>=3.10
License-File: LICENSE
Requires-Dist: chromadb>=1.3.5
Requires-Dist: qdrant-client>=1.7.0
Requires-Dist: python-dotenv>=0.21.0
Requires-Dist: mcp>=0.9.0
Requires-Dist: tree-sitter>=0.22.0
Requires-Dist: tree-sitter-python>=0.21.0
Requires-Dist: tree-sitter-javascript>=0.21.0
Requires-Dist: tree-sitter-typescript>=0.21.0
Requires-Dist: tree-sitter-go>=0.21.0
Requires-Dist: tree-sitter-rust>=0.21.0
Requires-Dist: tree-sitter-java>=0.21.0
Requires-Dist: tree-sitter-cpp>=0.21.0
Requires-Dist: tree-sitter-c>=0.21.0
Requires-Dist: fastapi>=0.104.0
Requires-Dist: uvicorn>=0.24.0
Requires-Dist: requests>=2.31.0
Provides-Extra: local
Requires-Dist: sentence-transformers>=2.2.0; extra == "local"
Requires-Dist: einops>=0.6.0; extra == "local"
Provides-Extra: cloud
Requires-Dist: openai>=1.50.0; extra == "cloud"
Requires-Dist: litellm>=1.0.0; extra == "cloud"
Provides-Extra: reranker
Requires-Dist: sentence-transformers>=2.2.0; extra == "reranker"
Provides-Extra: all
Requires-Dist: sentence-transformers>=2.2.0; extra == "all"
Requires-Dist: einops>=0.6.0; extra == "all"
Requires-Dist: openai>=1.50.0; extra == "all"
Requires-Dist: litellm>=1.0.0; extra == "all"
Provides-Extra: dev
Requires-Dist: pytest>=7.0.0; extra == "dev"
Requires-Dist: flake8>=6.0.0; extra == "dev"
Requires-Dist: black>=23.0.0; extra == "dev"
Requires-Dist: isort>=5.12.0; extra == "dev"
Requires-Dist: twine>=4.0.0; extra == "dev"
Requires-Dist: build>=1.0.0; extra == "dev"
Requires-Dist: pytest-asyncio>=0.21.0; extra == "dev"
Requires-Dist: pre-commit>=3.6.0; extra == "dev"
Dynamic: license-file
